covidpy/__init__.py
covidpy/errors.py
covidpy/lib.py
covidpy/types.py
covidpy/verifier.py
covidpy/certs/__init__.py
covidpy/certs/dsc-worker.key
covidpy/certs/dsc-worker.pem
CovidPyLib-0.1.4.dist-info/LICENSE
CovidPyLib-0.1.4.dist-info/METADATA
CovidPyLib-0.1.4.dist-info/WHEEL
CovidPyLib-0.1.4.dist-info/top_level.txt
CovidPyLib-0.1.4.dist-info/RECORD
