Metadata-Version: 2.1
Name: CovidPyLib
Version: 0.1.4
Summary: Simple Python library to work with DCCs (Digital Covid Certificates)
Home-page: https://github.com/CovidPyLib
Author: Doggy
License: GPLv3+
Project-URL: BugTracker, https://github.com/CovidPyLib/issues
Project-URL: Discussion, https://t.me/CovidPy
Project-URL: Source code, https://github.com/CovidPyLib/CovidPy
Project-URL: Docs, https://github.com/CovidPyLib/CovidPy
Keywords: Covid19 Covid DCC DGC scanner green pass
Platform: UNKNOWN
Classifier: Development Status :: 4 - Beta
Classifier: Intended Audience :: Developers
Classifier: Natural Language :: English
Classifier: License :: OSI Approved :: GNU General Public License v3 or later (GPLv3+)
Classifier: Operating System :: OS Independent
Classifier: Programming Language :: Python :: 3.7
Classifier: Programming Language :: Python :: 3.8
Classifier: Programming Language :: Python :: 3.9
Classifier: Programming Language :: Python :: 3.10
Classifier: Programming Language :: Python :: Implementation :: CPython
Classifier: Topic :: Software Development :: Libraries
Requires-Python: ~=3.7
License-File: LICENSE
Requires-Dist: schedule
Requires-Dist: requests
Requires-Dist: qrcode
Requires-Dist: pyzbar
Requires-Dist: cryptography (>=3.4.2)
Requires-Dist: cose
Requires-Dist: cbor2
Requires-Dist: base45 (>=0.4.3)
Requires-Dist: importlib
Requires-Dist: Pillow
